pollination/sky_view/__init__.py
pollination/sky_view/_postprocess.py
pollination/sky_view/_prepare_folder.py
pollination/sky_view/entry.py
pollination_sky_view-1.2.7.dist-info/LICENSE
pollination_sky_view-1.2.7.dist-info/METADATA
pollination_sky_view-1.2.7.dist-info/WHEEL
pollination_sky_view-1.2.7.dist-info/top_level.txt
pollination_sky_view-1.2.7.dist-info/RECORD
