Metadata-Version: 2.1
Name: pollination-sky-view
Version: 1.2.7
Summary: Recipe for computing sky view, sky exposure, and spherical (outdoor) exposure.
Home-page: https://github.com/pollination/sky-view
Author: ladybug-tools
Author-email: info@ladybug.tools
Maintainer: chris, ladybug-tools
Maintainer-email: chris@ladybug.tools, info@ladybug.tools
License: PolyForm Shield License 1.0.0, https://polyformproject.org/wp-content/uploads/2020/06/PolyForm-Shield-1.0.0.txt
Project-URL: icon, https://raw.githubusercontent.com/ladybug-tools/artwork/master/icons_components/honeybee/png/skyviewrecipe.png
Project-URL: docker, https://hub.docker.com/r/ladybugtools/honeybee-radiance
Keywords: honeybee,radiance,ladybug-tools,sky,view,exposure,spherical,sky-view
License-File: LICENSE
Requires-Dist: pollination-honeybee-radiance (>=0.22.42)
Requires-Dist: pollination-alias (>=0.11.8)
Requires-Dist: pollination-path (>=0.3.2)
Provides-Extra: viz
Requires-Dist: pollination-honeybee-display (>=0.1.13) ; extra == 'viz'
